{
  "ShowAddressesInCurrentBox": false,
  "Seed": "",
  "ShowControlsTooltip": false,
  "PlayerAddress": "a",
  "Signs": [
    {
      "Text": "Hello, and welcome.",
      "IsBeingEdited": false,
      "Address": "b",
      "X": 1,
      "Y": 0,
      "Symbol": "■",
      "Color": {
        "Item1": 200,
        "Item2": 200,
        "Item3": 100
      },
      "CreatedAt": "2025-07-27T21:31:09.5775959Z"
    },
    {
      "Text": "This is a sign. Walk on it to read it.",
      "IsBeingEdited": false,
      "Address": "c",
      "X": 2,
      "Y": 0,
      "Symbol": "■",
      "Color": {
        "Item1": 200,
        "Item2": 200,
        "Item3": 100
      },
      "CreatedAt": "2025-07-27T21:31:18.3304465Z"
    },
    {
      "Text": "The thing below is a vortex.",
      "IsBeingEdited": false,
      "Address": "d",
      "X": 3,
      "Y": 0,
      "Symbol": "■",
      "Color": {
        "Item1": 200,
        "Item2": 200,
        "Item3": 100
      },
      "CreatedAt": "2025-07-27T21:31:29.7511855Z"
    },
    {
      "Text": "Walk on it to teleport to another location.",
      "IsBeingEdited": false,
      "Address": "e",
      "X": 4,
      "Y": 0,
      "Symbol": "■",
      "Color": {
        "Item1": 200,
        "Item2": 200,
        "Item3": 100
      },
      "CreatedAt": "2025-07-27T21:31:50.4934004Z"
    },
    {
      "Text": "@The Hub: Page 1",
      "IsBeingEdited": false,
      "Address": "yh",
      "X": 2,
      "Y": 1,
      "Symbol": "■",
      "Color": {
        "Item1": 100,
        "Item2": 255,
        "Item3": 100
      },
      "CreatedAt": "2025-07-27T21:32:36.522711Z"
    },
    {
      "Text": "@Help",
      "IsBeingEdited": false,
      "Address": "yuh",
      "X": 2,
      "Y": 1,
      "Symbol": "■",
      "Color": {
        "Item1": 100,
        "Item2": 255,
        "Item3": 100
      },
      "CreatedAt": "2025-07-27T21:35:20.0765807Z"
    },
    {
      "Text": "Help",
      "IsBeingEdited": false,
      "Address": "yp",
      "X": 0,
      "Y": 3,
      "Symbol": "■",
      "Color": {
        "Item1": 200,
        "Item2": 200,
        "Item3": 100
      },
      "CreatedAt": "2025-07-27T21:35:30.3909967Z"
    },
    {
      "Text": "Vortex tutorial",
      "IsBeingEdited": false,
      "Address": "yup",
      "X": 0,
      "Y": 3,
      "Symbol": "■",
      "Color": {
        "Item1": 200,
        "Item2": 200,
        "Item3": 100
      },
      "CreatedAt": "2025-07-27T21:35:54.1879258Z"
    },
    {
      "Text": "A vortex is a portal.",
      "IsBeingEdited": false,
      "Address": "yuuk",
      "X": 0,
      "Y": 2,
      "Symbol": "■",
      "Color": {
        "Item1": 200,
        "Item2": 200,
        "Item3": 100
      },
      "CreatedAt": "2025-07-27T21:36:15.4848102Z"
    },
    {
      "Text": "It's an @ symbol, either blue or orange.",
      "IsBeingEdited": false,
      "Address": "yuul",
      "X": 1,
      "Y": 2,
      "Symbol": "■",
      "Color": {
        "Item1": 200,
        "Item2": 200,
        "Item3": 100
      },
      "CreatedAt": "2025-07-27T21:36:25.4610922Z"
    },
    {
      "Text": "A blue vortex is an enter vortex.",
      "IsBeingEdited": false,
      "Address": "yuum",
      "X": 2,
      "Y": 2,
      "Symbol": "■",
      "Color": {
        "Item1": 200,
        "Item2": 200,
        "Item3": 100
      },
      "CreatedAt": "2025-07-27T21:36:37.0887848Z"
    },
    {
      "Text": "An orange vortex is an exit vortex.",
      "IsBeingEdited": false,
      "Address": "yuun",
      "X": 3,
      "Y": 2,
      "Symbol": "■",
      "Color": {
        "Item1": 200,
        "Item2": 200,
        "Item3": 100
      },
      "CreatedAt": "2025-07-27T21:36:44.831849Z"
    },
    {
      "Text": "You can create a vortex by pressing N, then 1.",
      "IsBeingEdited": false,
      "Address": "yuuo",
      "X": 4,
      "Y": 2,
      "Symbol": "■",
      "Color": {
        "Item1": 200,
        "Item2": 200,
        "Item3": 100
      },
      "CreatedAt": "2025-07-27T21:36:52.7112744Z"
    },
    {
      "Text": "A vortex can be either one-way, or two-way.",
      "IsBeingEdited": false,
      "Address": "yuup",
      "X": 0,
      "Y": 3,
      "Symbol": "■",
      "Color": {
        "Item1": 200,
        "Item2": 200,
        "Item3": 100
      },
      "CreatedAt": "2025-07-27T21:37:07.5346664Z"
    },
    {
      "Text": "A one-way vortex teleports you to an address.",
      "IsBeingEdited": false,
      "Address": "yuuq",
      "X": 1,
      "Y": 3,
      "Symbol": "■",
      "Color": {
        "Item1": 200,
        "Item2": 200,
        "Item3": 100
      },
      "CreatedAt": "2025-07-27T21:38:13.94572Z"
    },
    {
      "Text": "A two-way vortex teleports you to another vortex.",
      "IsBeingEdited": false,
      "Address": "yuur",
      "X": 2,
      "Y": 3,
      "Symbol": "■",
      "Color": {
        "Item1": 200,
        "Item2": 200,
        "Item3": 100
      },
      "CreatedAt": "2025-07-27T21:38:27.4132051Z"
    },
    {
      "Text": "That vortex, an exit vortex, can take you back.",
      "IsBeingEdited": false,
      "Address": "yuus",
      "X": 3,
      "Y": 3,
      "Symbol": "■",
      "Color": {
        "Item1": 200,
        "Item2": 200,
        "Item3": 100
      },
      "CreatedAt": "2025-07-27T21:38:35.6014121Z"
    },
    {
      "Text": "You can delete a vortex by standing on top of it.",
      "IsBeingEdited": false,
      "Address": "yuut",
      "X": 4,
      "Y": 3,
      "Symbol": "■",
      "Color": {
        "Item1": 200,
        "Item2": 200,
        "Item3": 100
      },
      "CreatedAt": "2025-07-27T21:38:48.3826431Z"
    },
    {
      "Text": "Only entry vortexes (blue) can be deleted.",
      "IsBeingEdited": false,
      "Address": "yuuu",
      "X": 0,
      "Y": 4,
      "Symbol": "■",
      "Color": {
        "Item1": 200,
        "Item2": 200,
        "Item3": 100
      },
      "CreatedAt": "2025-07-27T21:39:08.3304051Z"
    },
    {
      "Text": "If you create a one-way vortex, you can delete it:",
      "IsBeingEdited": false,
      "Address": "yuuv",
      "X": 1,
      "Y": 4,
      "Symbol": "■",
      "Color": {
        "Item1": 200,
        "Item2": 200,
        "Item3": 100
      },
      "CreatedAt": "2025-07-27T21:39:17.0702139Z"
    },
    {
      "Text": "Create a two-way vortex pointing to its address,..",
      "IsBeingEdited": false,
      "Address": "yuuw",
      "X": 2,
      "Y": 4,
      "Symbol": "■",
      "Color": {
        "Item1": 200,
        "Item2": 200,
        "Item3": 100
      },
      "CreatedAt": "2025-07-27T21:39:31.8651904Z"
    },
    {
      "Text": "Then teleport to it, delete it, and delete...",
      "IsBeingEdited": false,
      "Address": "yuux",
      "X": 3,
      "Y": 4,
      "Symbol": "■",
      "Color": {
        "Item1": 200,
        "Item2": 200,
        "Item3": 100
      },
      "CreatedAt": "2025-07-27T21:39:51.3088208Z"
    },
    {
      "Text": "the helper two-way vortex (the entry vortex).",
      "IsBeingEdited": false,
      "Address": "yuuy",
      "X": 4,
      "Y": 4,
      "Symbol": "■",
      "Color": {
        "Item1": 200,
        "Item2": 200,
        "Item3": 100
      },
      "CreatedAt": "2025-07-27T21:40:01.8603722Z"
    },
    {
      "Text": "Please read from left to right like a book.",
      "IsBeingEdited": false,
      "Address": "yuuf",
      "X": 0,
      "Y": 1,
      "Symbol": "■",
      "Color": {
        "Item1": 200,
        "Item2": 200,
        "Item3": 100
      },
      "CreatedAt": "2025-07-27T21:42:01.7281318Z"
    },
    {
      "Text": "Vortex to the hub",
      "IsBeingEdited": false,
      "Address": "s",
      "X": 3,
      "Y": 3,
      "Symbol": "■",
      "Color": {
        "Item1": 200,
        "Item2": 200,
        "Item3": 100
      },
      "CreatedAt": "2025-07-27T21:42:54.5829729Z"
    },
    {
      "Text": "Dev room",
      "IsBeingEdited": false,
      "Address": "yt",
      "X": 4,
      "Y": 3,
      "Symbol": "■",
      "Color": {
        "Item1": 200,
        "Item2": 200,
        "Item3": 100
      },
      "CreatedAt": "2025-07-27T21:43:42.8363116Z"
    },
    {
      "Text": "Useful address list",
      "IsBeingEdited": false,
      "Address": "yq",
      "X": 1,
      "Y": 3,
      "Symbol": "■",
      "Color": {
        "Item1": 200,
        "Item2": 200,
        "Item3": 100
      },
      "CreatedAt": "2025-07-28T06:01:07.7855647Z"
    },
    {
      "Text": "Dev todo list: yyuh",
      "IsBeingEdited": false,
      "Address": "yvu",
      "X": 0,
      "Y": 4,
      "Symbol": "■",
      "Color": {
        "Item1": 200,
        "Item2": 200,
        "Item3": 100
      },
      "CreatedAt": "2025-07-28T06:01:14.5739012Z"
    },
    {
      "Text": "The Hub: ym",
      "IsBeingEdited": false,
      "Address": "yvv",
      "X": 1,
      "Y": 4,
      "Symbol": "■",
      "Color": {
        "Item1": 200,
        "Item2": 200,
        "Item3": 100
      },
      "CreatedAt": "2025-07-28T06:04:16.0323755Z"
    },
    {
      "Text": "Useful locations room: yvc",
      "IsBeingEdited": false,
      "Address": "yvk",
      "X": 0,
      "Y": 2,
      "Symbol": "■",
      "Color": {
        "Item1": 200,
        "Item2": 200,
        "Item3": 100
      },
      "CreatedAt": "2025-07-28T06:04:56.2273822Z"
    },
    {
      "Text": "Spawn: a",
      "IsBeingEdited": false,
      "Address": "yvl",
      "X": 1,
      "Y": 2,
      "Symbol": "■",
      "Color": {
        "Item1": 200,
        "Item2": 200,
        "Item3": 100
      },
      "CreatedAt": "2025-07-28T06:05:48.300487Z"
    },
    {
      "Text": "Tip: Press C to toggle controls visibility.",
      "IsBeingEdited": false,
      "Address": "m",
      "X": 2,
      "Y": 2,
      "Symbol": "■",
      "Color": {
        "Item1": 200,
        "Item2": 200,
        "Item3": 100
      },
      "CreatedAt": "2025-07-28T06:06:02.6998893Z"
    },
    {
      "Text": "Todo list",
      "IsBeingEdited": false,
      "Address": "yyp",
      "X": 0,
      "Y": 3,
      "Symbol": "■",
      "Color": {
        "Item1": 200,
        "Item2": 200,
        "Item3": 100
      },
      "CreatedAt": "2025-07-28T06:07:56.0796088Z"
    },
    {
      "Text": "Dev room: yym",
      "IsBeingEdited": false,
      "Address": "yvp",
      "X": 0,
      "Y": 3,
      "Symbol": "■",
      "Color": {
        "Item1": 200,
        "Item2": 200,
        "Item3": 100
      },
      "CreatedAt": "2025-07-28T06:08:42.4186827Z"
    },
    {
      "Text": "Maps",
      "IsBeingEdited": false,
      "Address": "yr",
      "X": 2,
      "Y": 3,
      "Symbol": "■",
      "Color": {
        "Item1": 200,
        "Item2": 200,
        "Item3": 100
      },
      "CreatedAt": "2025-07-28T06:10:41.5112037Z"
    },
    {
      "Text": "Map 1",
      "IsBeingEdited": false,
      "Address": "ywp",
      "X": 0,
      "Y": 3,
      "Symbol": "■",
      "Color": {
        "Item1": 200,
        "Item2": 200,
        "Item3": 100
      },
      "CreatedAt": "2025-07-28T06:10:52.9646219Z"
    },
    {
      "Text": "Test maps",
      "IsBeingEdited": false,
      "Address": "ywt",
      "X": 4,
      "Y": 3,
      "Symbol": "■",
      "Color": {
        "Item1": 200,
        "Item2": 200,
        "Item3": 100
      },
      "CreatedAt": "2025-07-28T06:14:04.9856552Z"
    },
    {
      "Text": "About this map",
      "IsBeingEdited": false,
      "Address": "ywyp",
      "X": 0,
      "Y": 3,
      "Symbol": "■",
      "Color": {
        "Item1": 200,
        "Item2": 200,
        "Item3": 100
      },
      "CreatedAt": "2025-07-28T06:14:21.4025125Z"
    },
    {
      "Text": "This is a collection of maps used to test game",
      "IsBeingEdited": false,
      "Address": "ywyub",
      "X": 1,
      "Y": 0,
      "Symbol": "■",
      "Color": {
        "Item1": 200,
        "Item2": 200,
        "Item3": 100
      },
      "CreatedAt": "2025-07-28T06:14:28.909242Z"
    },
    {
      "Text": "features.",
      "IsBeingEdited": false,
      "Address": "ywyuc",
      "X": 2,
      "Y": 0,
      "Symbol": "■",
      "Color": {
        "Item1": 200,
        "Item2": 200,
        "Item3": 100
      },
      "CreatedAt": "2025-07-28T06:14:40.4456929Z"
    },
    {
      "Text": "Main",
      "IsBeingEdited": false,
      "Address": "ywyt",
      "X": 4,
      "Y": 3,
      "Symbol": "■",
      "Color": {
        "Item1": 200,
        "Item2": 200,
        "Item3": 100
      },
      "CreatedAt": "2025-07-28T06:15:22.3696805Z"
    },
    {
      "Text": "Games",
      "IsBeingEdited": false,
      "Address": "ywup",
      "X": 0,
      "Y": 3,
      "Symbol": "■",
      "Color": {
        "Item1": 200,
        "Item2": 200,
        "Item3": 100
      },
      "CreatedAt": "2025-07-28T06:18:15.0933404Z"
    },
    {
      "Text": "Mazes",
      "IsBeingEdited": false,
      "Address": "ywuup",
      "X": 0,
      "Y": 3,
      "Symbol": "■",
      "Color": {
        "Item1": 200,
        "Item2": 200,
        "Item3": 100
      },
      "CreatedAt": "2025-07-28T06:18:20.352451Z"
    },
    {
      "Text": "Maze 1",
      "IsBeingEdited": false,
      "Address": "ywuuup",
      "X": 0,
      "Y": 3,
      "Symbol": "■",
      "Color": {
        "Item1": 200,
        "Item2": 200,
        "Item3": 100
      },
      "CreatedAt": "2025-07-28T06:18:30.773241Z"
    },
    {
      "Text": "Here, you will respawn if you enter a wrong vortex",
      "IsBeingEdited": false,
      "Address": "ywuuuue",
      "X": 4,
      "Y": 0,
      "Symbol": "■",
      "Color": {
        "Item1": 200,
        "Item2": 200,
        "Item3": 100
      },
      "CreatedAt": "2025-07-28T06:19:20.3391155Z"
    },
    {
      "Text": "Avoid the vortexes!",
      "IsBeingEdited": false,
      "Address": "ywuuuuj",
      "X": 4,
      "Y": 1,
      "Symbol": "■",
      "Color": {
        "Item1": 200,
        "Item2": 200,
        "Item3": 100
      },
      "CreatedAt": "2025-07-28T06:19:28.6709325Z"
    },
    {
      "Text": "Read from top down:",
      "IsBeingEdited": false,
      "Address": "ywuuuud",
      "X": 3,
      "Y": 0,
      "Symbol": "■",
      "Color": {
        "Item1": 200,
        "Item2": 200,
        "Item3": 100
      },
      "CreatedAt": "2025-07-28T06:19:38.4751059Z"
    },
    {
      "Text": "Good luck! Enter the vortex to begin.",
      "IsBeingEdited": false,
      "Address": "ywuuuuo",
      "X": 4,
      "Y": 2,
      "Symbol": "■",
      "Color": {
        "Item1": 200,
        "Item2": 200,
        "Item3": 100
      },
      "CreatedAt": "2025-07-28T06:19:45.1331339Z"
    },
    {
      "Text": "After entering, move right.",
      "IsBeingEdited": false,
      "Address": "ywuuuut",
      "X": 4,
      "Y": 3,
      "Symbol": "■",
      "Color": {
        "Item1": 200,
        "Item2": 200,
        "Item3": 100
      },
      "CreatedAt": "2025-07-28T06:23:15.1473901Z"
    },
    {
      "Text": "-->",
      "IsBeingEdited": false,
      "Address": "ywuuuuwx",
      "X": 3,
      "Y": 4,
      "Symbol": "■",
      "Color": {
        "Item1": 200,
        "Item2": 200,
        "Item3": 100
      },
      "CreatedAt": "2025-07-28T06:28:34.1372602Z"
    },
    {
      "Text": "Enter the vortex at \"y\" to finish.",
      "IsBeingEdited": false,
      "Address": "ywuuuuy",
      "X": 4,
      "Y": 4,
      "Symbol": "■",
      "Color": {
        "Item1": 200,
        "Item2": 200,
        "Item3": 100
      },
      "CreatedAt": "2025-07-28T06:28:51.8067541Z"
    },
    {
      "Text": "@Spawn",
      "IsBeingEdited": false,
      "Address": "u",
      "X": 0,
      "Y": 4,
      "Symbol": "■",
      "Color": {
        "Item1": 100,
        "Item2": 255,
        "Item3": 100
      },
      "CreatedAt": "2025-07-28T06:36:09.3597055Z"
    },
    {
      "Text": "Sign tutorial",
      "IsBeingEdited": false,
      "Address": "yuq",
      "X": 1,
      "Y": 3,
      "Symbol": "■",
      "Color": {
        "Item1": 200,
        "Item2": 200,
        "Item3": 100
      },
      "CreatedAt": "2025-07-28T06:37:55.2946723Z"
    },
    {
      "Text": "@Vortex tutorial",
      "IsBeingEdited": false,
      "Address": "yuue",
      "X": 4,
      "Y": 0,
      "Symbol": "■",
      "Color": {
        "Item1": 100,
        "Item2": 255,
        "Item3": 100
      },
      "CreatedAt": "2025-07-28T06:38:28.3870186Z"
    },
    {
      "Text": "A sign can be created using T.",
      "IsBeingEdited": false,
      "Address": "yuvk",
      "X": 0,
      "Y": 2,
      "Symbol": "■",
      "Color": {
        "Item1": 200,
        "Item2": 200,
        "Item3": 100
      },
      "CreatedAt": "2025-07-28T06:38:41.9211064Z"
    },
    {
      "Text": "When standing on a sign, press T to edit it.",
      "IsBeingEdited": false,
      "Address": "yuvl",
      "X": 1,
      "Y": 2,
      "Symbol": "■",
      "Color": {
        "Item1": 200,
        "Item2": 200,
        "Item3": 100
      },
      "CreatedAt": "2025-07-28T06:38:48.5715194Z"
    },
    {
      "Text": "Once editing, type the text and...",
      "IsBeingEdited": false,
      "Address": "yuvm",
      "X": 2,
      "Y": 2,
      "Symbol": "■",
      "Color": {
        "Item1": 200,
        "Item2": 200,
        "Item3": 100
      },
      "CreatedAt": "2025-07-28T06:38:59.8341856Z"
    },
    {
      "Text": "Press Enter to confirm or Escape to cancel.",
      "IsBeingEdited": false,
      "Address": "yuvn",
      "X": 3,
      "Y": 2,
      "Symbol": "■",
      "Color": {
        "Item1": 200,
        "Item2": 200,
        "Item3": 100
      },
      "CreatedAt": "2025-07-28T06:39:13.2934503Z"
    },
    {
      "Text": "Press X to delete a sign.",
      "IsBeingEdited": false,
      "Address": "yuvo",
      "X": 4,
      "Y": 2,
      "Symbol": "■",
      "Color": {
        "Item1": 200,
        "Item2": 200,
        "Item3": 100
      },
      "CreatedAt": "2025-07-28T06:39:22.7905811Z"
    },
    {
      "Text": "Read from left to right!",
      "IsBeingEdited": false,
      "Address": "yuvf",
      "X": 0,
      "Y": 1,
      "Symbol": "■",
      "Color": {
        "Item1": 200,
        "Item2": 200,
        "Item3": 100
      },
      "CreatedAt": "2025-07-28T06:39:31.3861705Z"
    },
    {
      "Text": "@Sign tutorial",
      "IsBeingEdited": false,
      "Address": "yuve",
      "X": 4,
      "Y": 0,
      "Symbol": "■",
      "Color": {
        "Item1": 100,
        "Item2": 255,
        "Item3": 100
      },
      "CreatedAt": "2025-07-28T06:39:37.1859583Z"
    },
    {
      "Text": "To name an entire box, start your sign with @.",
      "IsBeingEdited": false,
      "Address": "yuvp",
      "X": 0,
      "Y": 3,
      "Symbol": "■",
      "Color": {
        "Item1": 200,
        "Item2": 200,
        "Item3": 100
      },
      "CreatedAt": "2025-07-28T06:39:44.8722202Z"
    },
    {
      "Text": "The box name will show up across the whole box.",
      "IsBeingEdited": false,
      "Address": "yuvq",
      "X": 1,
      "Y": 3,
      "Symbol": "■",
      "Color": {
        "Item1": 200,
        "Item2": 200,
        "Item3": 100
      },
      "CreatedAt": "2025-07-28T06:40:17.5792486Z"
    },
    {
      "Text": "The box name sign will be green.",
      "IsBeingEdited": false,
      "Address": "yuvr",
      "X": 2,
      "Y": 3,
      "Symbol": "■",
      "Color": {
        "Item1": 200,
        "Item2": 200,
        "Item3": 100
      },
      "CreatedAt": "2025-07-28T06:40:27.8558308Z"
    },
    {
      "Text": "Tip: To create long texts, you can use vortexes...",
      "IsBeingEdited": false,
      "Address": "yuvs",
      "X": 3,
      "Y": 3,
      "Symbol": "■",
      "Color": {
        "Item1": 200,
        "Item2": 200,
        "Item3": 100
      },
      "CreatedAt": "2025-07-28T06:40:38.8553787Z"
    },
    {
      "Text": "at the edge of rooms to make the player only",
      "IsBeingEdited": false,
      "Address": "yuvt",
      "X": 4,
      "Y": 3,
      "Symbol": "■",
      "Color": {
        "Item1": 200,
        "Item2": 200,
        "Item3": 100
      },
      "CreatedAt": "2025-07-28T06:40:52.7746781Z"
    },
    {
      "Text": "have to move in one direction to read.",
      "IsBeingEdited": false,
      "Address": "yuvu",
      "X": 0,
      "Y": 4,
      "Symbol": "■",
      "Color": {
        "Item1": 200,
        "Item2": 200,
        "Item3": 100
      },
      "CreatedAt": "2025-07-28T06:41:08.9593867Z"
    },
    {
      "Text": "If a text is too long, just put a vortex",
      "IsBeingEdited": false,
      "Address": "yuvv",
      "X": 1,
      "Y": 4,
      "Symbol": "■",
      "Color": {
        "Item1": 200,
        "Item2": 200,
        "Item3": 100
      },
      "CreatedAt": "2025-07-28T06:41:17.7016944Z"
    },
    {
      "Text": "at the end of it. Space is unlimited!",
      "IsBeingEdited": false,
      "Address": "yuvw",
      "X": 2,
      "Y": 4,
      "Symbol": "■",
      "Color": {
        "Item1": 200,
        "Item2": 200,
        "Item3": 100
      },
      "CreatedAt": "2025-07-28T06:41:24.1014056Z"
    },
    {
      "Text": "@Maps",
      "IsBeingEdited": false,
      "Address": "ywh",
      "X": 2,
      "Y": 1,
      "Symbol": "■",
      "Color": {
        "Item1": 100,
        "Item2": 255,
        "Item3": 100
      },
      "CreatedAt": "2025-07-28T06:45:17.3338694Z"
    },
    {
      "Text": "@Test maps",
      "IsBeingEdited": false,
      "Address": "ywyh",
      "X": 2,
      "Y": 1,
      "Symbol": "■",
      "Color": {
        "Item1": 100,
        "Item2": 255,
        "Item3": 100
      },
      "CreatedAt": "2025-07-28T06:45:22.8589379Z"
    },
    {
      "Text": "@Map 1",
      "IsBeingEdited": false,
      "Address": "ywuh",
      "X": 2,
      "Y": 1,
      "Symbol": "■",
      "Color": {
        "Item1": 100,
        "Item2": 255,
        "Item3": 100
      },
      "CreatedAt": "2025-07-28T06:45:29.5606141Z"
    },
    {
      "Text": "@Map 1: Games",
      "IsBeingEdited": false,
      "Address": "ywuuh",
      "X": 2,
      "Y": 1,
      "Symbol": "■",
      "Color": {
        "Item1": 100,
        "Item2": 255,
        "Item3": 100
      },
      "CreatedAt": "2025-07-28T06:45:37.1737586Z"
    },
    {
      "Text": "@Mazes",
      "IsBeingEdited": false,
      "Address": "ywuuuh",
      "X": 2,
      "Y": 1,
      "Symbol": "■",
      "Color": {
        "Item1": 100,
        "Item2": 255,
        "Item3": 100
      },
      "CreatedAt": "2025-07-28T06:45:45.8978455Z"
    },
    {
      "Text": "@Maze 1 Spawn",
      "IsBeingEdited": false,
      "Address": "ywuuuuh",
      "X": 2,
      "Y": 1,
      "Symbol": "■",
      "Color": {
        "Item1": 100,
        "Item2": 255,
        "Item3": 100
      },
      "CreatedAt": "2025-07-28T06:46:00.554127Z"
    },
    {
      "Text": "@Maze 1",
      "IsBeingEdited": false,
      "Address": "ywuuuuwb",
      "X": 1,
      "Y": 0,
      "Symbol": "■",
      "Color": {
        "Item1": 100,
        "Item2": 255,
        "Item3": 100
      },
      "CreatedAt": "2025-07-28T06:46:16.4103943Z"
    },
    {
      "Text": "The Hub: Page 2",
      "IsBeingEdited": false,
      "Address": "ys",
      "X": 3,
      "Y": 3,
      "Symbol": "■",
      "Color": {
        "Item1": 200,
        "Item2": 200,
        "Item3": 100
      },
      "CreatedAt": "2025-07-28T06:48:55.6380473Z"
    },
    {
      "Text": "@The Hub: Page 2",
      "IsBeingEdited": false,
      "Address": "yxh",
      "X": 2,
      "Y": 1,
      "Symbol": "■",
      "Color": {
        "Item1": 100,
        "Item2": 255,
        "Item3": 100
      },
      "CreatedAt": "2025-07-28T06:49:18.1355212Z"
    },
    {
      "Text": "Back to page 1",
      "IsBeingEdited": false,
      "Address": "yxf",
      "X": 0,
      "Y": 1,
      "Symbol": "■",
      "Color": {
        "Item1": 200,
        "Item2": 200,
        "Item3": 100
      },
      "CreatedAt": "2025-07-28T06:50:26.6340312Z"
    }
  ],
  "Vortexes": [
    {
      "TargetAddress": "ya",
      "IsEntry": true,
      "PairedVortexAddress": "ya",
      "IsOneWay": false,
      "Address": "y",
      "X": 4,
      "Y": 4,
      "Symbol": "@",
      "Color": {
        "Item1": 30,
        "Item2": 144,
        "Item3": 255
      },
      "CreatedAt": "2025-07-27T21:26:44.7906697Z"
    },
    {
      "TargetAddress": "y",
      "IsEntry": false,
      "PairedVortexAddress": "y",
      "IsOneWay": false,
      "Address": "ya",
      "X": 0,
      "Y": 0,
      "Symbol": "@",
      "Color": {
        "Item1": 255,
        "Item2": 165,
        "Item3": 0
      },
      "CreatedAt": "2025-07-27T21:26:44.7907781Z"
    },
    {
      "TargetAddress": "yua",
      "IsEntry": true,
      "PairedVortexAddress": "yua",
      "IsOneWay": false,
      "Address": "yu",
      "X": 0,
      "Y": 4,
      "Symbol": "@",
      "Color": {
        "Item1": 30,
        "Item2": 144,
        "Item3": 255
      },
      "CreatedAt": "2025-07-27T21:35:15.0778037Z"
    },
    {
      "TargetAddress": "yu",
      "IsEntry": false,
      "PairedVortexAddress": "yu",
      "IsOneWay": false,
      "Address": "yua",
      "X": 0,
      "Y": 0,
      "Symbol": "@",
      "Color": {
        "Item1": 255,
        "Item2": 165,
        "Item3": 0
      },
      "CreatedAt": "2025-07-27T21:35:15.0778049Z"
    },
    {
      "TargetAddress": "yuua",
      "IsEntry": true,
      "PairedVortexAddress": "yuua",
      "IsOneWay": false,
      "Address": "yuu",
      "X": 0,
      "Y": 4,
      "Symbol": "@",
      "Color": {
        "Item1": 30,
        "Item2": 144,
        "Item3": 255
      },
      "CreatedAt": "2025-07-27T21:35:43.4555462Z"
    },
    {
      "TargetAddress": "yuu",
      "IsEntry": false,
      "PairedVortexAddress": "yuu",
      "IsOneWay": false,
      "Address": "yuua",
      "X": 0,
      "Y": 0,
      "Symbol": "@",
      "Color": {
        "Item1": 255,
        "Item2": 165,
        "Item3": 0
      },
      "CreatedAt": "2025-07-27T21:35:43.4555476Z"
    },
    {
      "TargetAddress": "yya",
      "IsEntry": true,
      "PairedVortexAddress": "yya",
      "IsOneWay": false,
      "Address": "yy",
      "X": 4,
      "Y": 4,
      "Symbol": "@",
      "Color": {
        "Item1": 30,
        "Item2": 144,
        "Item3": 255
      },
      "CreatedAt": "2025-07-27T21:43:41.4909944Z"
    },
    {
      "TargetAddress": "yy",
      "IsEntry": false,
      "PairedVortexAddress": "yy",
      "IsOneWay": false,
      "Address": "yya",
      "X": 0,
      "Y": 0,
      "Symbol": "@",
      "Color": {
        "Item1": 255,
        "Item2": 165,
        "Item3": 0
      },
      "CreatedAt": "2025-07-27T21:43:41.4909954Z"
    },
    {
      "TargetAddress": "yva",
      "IsEntry": true,
      "PairedVortexAddress": "yva",
      "IsOneWay": false,
      "Address": "yv",
      "X": 1,
      "Y": 4,
      "Symbol": "@",
      "Color": {
        "Item1": 30,
        "Item2": 144,
        "Item3": 255
      },
      "CreatedAt": "2025-07-28T06:01:06.4024008Z"
    },
    {
      "TargetAddress": "yv",
      "IsEntry": false,
      "PairedVortexAddress": "yv",
      "IsOneWay": false,
      "Address": "yva",
      "X": 0,
      "Y": 0,
      "Symbol": "@",
      "Color": {
        "Item1": 255,
        "Item2": 165,
        "Item3": 0
      },
      "CreatedAt": "2025-07-28T06:01:06.4024018Z"
    },
    {
      "TargetAddress": "ywa",
      "IsEntry": true,
      "PairedVortexAddress": "ywa",
      "IsOneWay": false,
      "Address": "yw",
      "X": 2,
      "Y": 4,
      "Symbol": "@",
      "Color": {
        "Item1": 30,
        "Item2": 144,
        "Item3": 255
      },
      "CreatedAt": "2025-07-28T06:10:40.8104607Z"
    },
    {
      "TargetAddress": "yw",
      "IsEntry": false,
      "PairedVortexAddress": "yw",
      "IsOneWay": false,
      "Address": "ywa",
      "X": 0,
      "Y": 0,
      "Symbol": "@",
      "Color": {
        "Item1": 255,
        "Item2": 165,
        "Item3": 0
      },
      "CreatedAt": "2025-07-28T06:10:40.8104616Z"
    },
    {
      "TargetAddress": "ywua",
      "IsEntry": true,
      "PairedVortexAddress": "ywua",
      "IsOneWay": false,
      "Address": "ywu",
      "X": 0,
      "Y": 4,
      "Symbol": "@",
      "Color": {
        "Item1": 30,
        "Item2": 144,
        "Item3": 255
      },
      "CreatedAt": "2025-07-28T06:11:09.5661449Z"
    },
    {
      "TargetAddress": "ywu",
      "IsEntry": false,
      "PairedVortexAddress": "ywu",
      "IsOneWay": false,
      "Address": "ywua",
      "X": 0,
      "Y": 0,
      "Symbol": "@",
      "Color": {
        "Item1": 255,
        "Item2": 165,
        "Item3": 0
      },
      "CreatedAt": "2025-07-28T06:11:09.5661463Z"
    },
    {
      "TargetAddress": "ywya",
      "IsEntry": true,
      "PairedVortexAddress": "ywya",
      "IsOneWay": false,
      "Address": "ywy",
      "X": 4,
      "Y": 4,
      "Symbol": "@",
      "Color": {
        "Item1": 30,
        "Item2": 144,
        "Item3": 255
      },
      "CreatedAt": "2025-07-28T06:14:10.7116525Z"
    },
    {
      "TargetAddress": "ywy",
      "IsEntry": false,
      "PairedVortexAddress": "ywy",
      "IsOneWay": false,
      "Address": "ywya",
      "X": 0,
      "Y": 0,
      "Symbol": "@",
      "Color": {
        "Item1": 255,
        "Item2": 165,
        "Item3": 0
      },
      "CreatedAt": "2025-07-28T06:14:10.7116536Z"
    },
    {
      "TargetAddress": "ywyua",
      "IsEntry": true,
      "PairedVortexAddress": "ywyua",
      "IsOneWay": false,
      "Address": "ywyu",
      "X": 0,
      "Y": 4,
      "Symbol": "@",
      "Color": {
        "Item1": 30,
        "Item2": 144,
        "Item3": 255
      },
      "CreatedAt": "2025-07-28T06:14:20.5736282Z"
    },
    {
      "TargetAddress": "ywyu",
      "IsEntry": false,
      "PairedVortexAddress": "ywyu",
      "IsOneWay": false,
      "Address": "ywyua",
      "X": 0,
      "Y": 0,
      "Symbol": "@",
      "Color": {
        "Item1": 255,
        "Item2": 165,
        "Item3": 0
      },
      "CreatedAt": "2025-07-28T06:14:20.5736291Z"
    },
    {
      "TargetAddress": "ywyya",
      "IsEntry": true,
      "PairedVortexAddress": "ywyya",
      "IsOneWay": false,
      "Address": "ywyy",
      "X": 4,
      "Y": 4,
      "Symbol": "@",
      "Color": {
        "Item1": 30,
        "Item2": 144,
        "Item3": 255
      },
      "CreatedAt": "2025-07-28T06:15:21.7713978Z"
    },
    {
      "TargetAddress": "ywyy",
      "IsEntry": false,
      "PairedVortexAddress": "ywyy",
      "IsOneWay": false,
      "Address": "ywyya",
      "X": 0,
      "Y": 0,
      "Symbol": "@",
      "Color": {
        "Item1": 255,
        "Item2": 165,
        "Item3": 0
      },
      "CreatedAt": "2025-07-28T06:15:21.7713986Z"
    },
    {
      "TargetAddress": "ywuua",
      "IsEntry": true,
      "PairedVortexAddress": "ywuua",
      "IsOneWay": false,
      "Address": "ywuu",
      "X": 0,
      "Y": 4,
      "Symbol": "@",
      "Color": {
        "Item1": 30,
        "Item2": 144,
        "Item3": 255
      },
      "CreatedAt": "2025-07-28T06:18:17.2371227Z"
    },
    {
      "TargetAddress": "ywuu",
      "IsEntry": false,
      "PairedVortexAddress": "ywuu",
      "IsOneWay": false,
      "Address": "ywuua",
      "X": 0,
      "Y": 0,
      "Symbol": "@",
      "Color": {
        "Item1": 255,
        "Item2": 165,
        "Item3": 0
      },
      "CreatedAt": "2025-07-28T06:18:17.2371237Z"
    },
    {
      "TargetAddress": "ywuuua",
      "IsEntry": true,
      "PairedVortexAddress": "ywuuua",
      "IsOneWay": false,
      "Address": "ywuuu",
      "X": 0,
      "Y": 4,
      "Symbol": "@",
      "Color": {
        "Item1": 30,
        "Item2": 144,
        "Item3": 255
      },
      "CreatedAt": "2025-07-28T06:18:24.8766597Z"
    },
    {
      "TargetAddress": "ywuuu",
      "IsEntry": false,
      "PairedVortexAddress": "ywuuu",
      "IsOneWay": false,
      "Address": "ywuuua",
      "X": 0,
      "Y": 0,
      "Symbol": "@",
      "Color": {
        "Item1": 255,
        "Item2": 165,
        "Item3": 0
      },
      "CreatedAt": "2025-07-28T06:18:24.8766605Z"
    },
    {
      "TargetAddress": "ywuuuua",
      "IsEntry": true,
      "PairedVortexAddress": "ywuuuua",
      "IsOneWay": false,
      "Address": "ywuuuu",
      "X": 0,
      "Y": 4,
      "Symbol": "@",
      "Color": {
        "Item1": 30,
        "Item2": 144,
        "Item3": 255
      },
      "CreatedAt": "2025-07-28T06:18:34.8596835Z"
    },
    {
      "TargetAddress": "ywuuuu",
      "IsEntry": false,
      "PairedVortexAddress": "ywuuuu",
      "IsOneWay": false,
      "Address": "ywuuuua",
      "X": 0,
      "Y": 0,
      "Symbol": "@",
      "Color": {
        "Item1": 255,
        "Item2": 165,
        "Item3": 0
      },
      "CreatedAt": "2025-07-28T06:18:34.8596844Z"
    },
    {
      "TargetAddress": "ywuuuuwa",
      "IsEntry": true,
      "PairedVortexAddress": "ywuuuuwa",
      "IsOneWay": false,
      "Address": "ywuuuuw",
      "X": 2,
      "Y": 4,
      "Symbol": "@",
      "Color": {
        "Item1": 30,
        "Item2": 144,
        "Item3": 255
      },
      "CreatedAt": "2025-07-28T06:19:58.3599004Z"
    },
    {
      "TargetAddress": "ywuuuuw",
      "IsEntry": false,
      "PairedVortexAddress": "ywuuuuw",
      "IsOneWay": false,
      "Address": "ywuuuuwa",
      "X": 0,
      "Y": 0,
      "Symbol": "@",
      "Color": {
        "Item1": 255,
        "Item2": 165,
        "Item3": 0
      },
      "CreatedAt": "2025-07-28T06:19:58.3599017Z"
    },
    {
      "TargetAddress": "ywuuuum",
      "IsEntry": true,
      "PairedVortexAddress": "",
      "IsOneWay": true,
      "Address": "ywuuuuwf",
      "X": 0,
      "Y": 1,
      "Symbol": "@",
      "Color": {
        "Item1": 30,
        "Item2": 144,
        "Item3": 255
      },
      "CreatedAt": "2025-07-28T06:20:54.6695818Z"
    },
    {
      "TargetAddress": "ywuuuum",
      "IsEntry": true,
      "PairedVortexAddress": "",
      "IsOneWay": true,
      "Address": "ywuuuuwg",
      "X": 1,
      "Y": 1,
      "Symbol": "@",
      "Color": {
        "Item1": 30,
        "Item2": 144,
        "Item3": 255
      },
      "CreatedAt": "2025-07-28T06:24:42.6594742Z"
    },
    {
      "TargetAddress": "ywuuuum",
      "IsEntry": true,
      "PairedVortexAddress": "",
      "IsOneWay": true,
      "Address": "ywuuuuwh",
      "X": 2,
      "Y": 1,
      "Symbol": "@",
      "Color": {
        "Item1": 30,
        "Item2": 144,
        "Item3": 255
      },
      "CreatedAt": "2025-07-28T06:27:44.1644312Z"
    },
    {
      "TargetAddress": "ywuuuum",
      "IsEntry": true,
      "PairedVortexAddress": "",
      "IsOneWay": true,
      "Address": "ywuuuuwi",
      "X": 3,
      "Y": 1,
      "Symbol": "@",
      "Color": {
        "Item1": 30,
        "Item2": 144,
        "Item3": 255
      },
      "CreatedAt": "2025-07-28T06:27:54.9026493Z"
    },
    {
      "TargetAddress": "ywuuuum",
      "IsEntry": true,
      "PairedVortexAddress": "",
      "IsOneWay": true,
      "Address": "ywuuuuwt",
      "X": 4,
      "Y": 3,
      "Symbol": "@",
      "Color": {
        "Item1": 30,
        "Item2": 144,
        "Item3": 255
      },
      "CreatedAt": "2025-07-28T06:28:07.686447Z"
    },
    {
      "TargetAddress": "ywuuuum",
      "IsEntry": true,
      "PairedVortexAddress": "",
      "IsOneWay": true,
      "Address": "ywuuuuws",
      "X": 3,
      "Y": 3,
      "Symbol": "@",
      "Color": {
        "Item1": 30,
        "Item2": 144,
        "Item3": 255
      },
      "CreatedAt": "2025-07-28T06:28:11.7944286Z"
    },
    {
      "TargetAddress": "ywuuuum",
      "IsEntry": true,
      "PairedVortexAddress": "",
      "IsOneWay": true,
      "Address": "ywuuuuwr",
      "X": 2,
      "Y": 3,
      "Symbol": "@",
      "Color": {
        "Item1": 30,
        "Item2": 144,
        "Item3": 255
      },
      "CreatedAt": "2025-07-28T06:28:16.0153757Z"
    },
    {
      "TargetAddress": "ywuuuum",
      "IsEntry": true,
      "PairedVortexAddress": "",
      "IsOneWay": true,
      "Address": "ywuuuuwq",
      "X": 1,
      "Y": 3,
      "Symbol": "@",
      "Color": {
        "Item1": 30,
        "Item2": 144,
        "Item3": 255
      },
      "CreatedAt": "2025-07-28T06:28:19.9779801Z"
    },
    {
      "TargetAddress": "ywuuuuwya",
      "IsEntry": true,
      "PairedVortexAddress": "ywuuuuwya",
      "IsOneWay": false,
      "Address": "ywuuuuwy",
      "X": 4,
      "Y": 4,
      "Symbol": "@",
      "Color": {
        "Item1": 30,
        "Item2": 144,
        "Item3": 255
      },
      "CreatedAt": "2025-07-28T06:28:30.3991055Z"
    },
    {
      "TargetAddress": "ywuuuuwy",
      "IsEntry": false,
      "PairedVortexAddress": "ywuuuuwy",
      "IsOneWay": false,
      "Address": "ywuuuuwya",
      "X": 0,
      "Y": 0,
      "Symbol": "@",
      "Color": {
        "Item1": 255,
        "Item2": 165,
        "Item3": 0
      },
      "CreatedAt": "2025-07-28T06:28:30.3991065Z"
    },
    {
      "TargetAddress": "yuva",
      "IsEntry": true,
      "PairedVortexAddress": "yuva",
      "IsOneWay": false,
      "Address": "yuv",
      "X": 1,
      "Y": 4,
      "Symbol": "@",
      "Color": {
        "Item1": 30,
        "Item2": 144,
        "Item3": 255
      },
      "CreatedAt": "2025-07-28T06:37:54.5950552Z"
    },
    {
      "TargetAddress": "yuv",
      "IsEntry": false,
      "PairedVortexAddress": "yuv",
      "IsOneWay": false,
      "Address": "yuva",
      "X": 0,
      "Y": 0,
      "Symbol": "@",
      "Color": {
        "Item1": 255,
        "Item2": 165,
        "Item3": 0
      },
      "CreatedAt": "2025-07-28T06:37:54.5950564Z"
    },
    {
      "TargetAddress": "yxa",
      "IsEntry": true,
      "PairedVortexAddress": "yxa",
      "IsOneWay": false,
      "Address": "yx",
      "X": 3,
      "Y": 4,
      "Symbol": "@",
      "Color": {
        "Item1": 30,
        "Item2": 144,
        "Item3": 255
      },
      "CreatedAt": "2025-07-28T06:49:09.6701103Z"
    },
    {
      "TargetAddress": "yx",
      "IsEntry": false,
      "PairedVortexAddress": "yx",
      "IsOneWay": false,
      "Address": "yxa",
      "X": 0,
      "Y": 0,
      "Symbol": "@",
      "Color": {
        "Item1": 255,
        "Item2": 165,
        "Item3": 0
      },
      "CreatedAt": "2025-07-28T06:49:09.670115Z"
    }
  ]
}